safe_writer.py
safe_writer-0.9.3.data/scripts/safe_writer.py
safe_writer-0.9.3.dist-info/LICENSE
safe_writer-0.9.3.dist-info/METADATA
safe_writer-0.9.3.dist-info/WHEEL
safe_writer-0.9.3.dist-info/top_level.txt
safe_writer-0.9.3.dist-info/RECORD
